eodash_catalog/__about__.py
eodash_catalog/__init__.py
eodash_catalog/duration.py
eodash_catalog/endpoints.py
eodash_catalog/generate_indicators.py
eodash_catalog/sh_endpoint.py
eodash_catalog/stac_handling.py
eodash_catalog/thumbnails.py
eodash_catalog/utils.py
eodash_catalog-0.3.34.dist-info/METADATA
eodash_catalog-0.3.34.dist-info/WHEEL
eodash_catalog-0.3.34.dist-info/entry_points.txt
eodash_catalog-0.3.34.dist-info/licenses/LICENSE.txt
eodash_catalog-0.3.34.dist-info/RECORD
