Metadata-Version: 2.4
Name: eodash_catalog
Version: 0.3.34
Summary: This package is intended to help create a compatible STAC catalog for the eodash dashboard client. It supports configuration of multiple endpoint types for information extraction.
Project-URL: Documentation, https://github.com/eodash/eodash_catalog#readme
Project-URL: Issues, https://github.com/eodash/eodash_catalog/issues
Project-URL: Source, https://github.com/eodash/eodash_catalog
Author-email: Daniel Santillan <daniel.santillan@eox.at>
License-Expression: MIT
License-File: LICENSE.txt
Classifier: Development Status :: 4 - Beta
Classifier: Programming Language :: Python
Classifier: Programming Language :: Python :: 3.10
Classifier: Programming Language :: Python :: 3.11
Classifier: Programming Language :: Python :: 3.12
Classifier: Programming Language :: Python :: Implementation :: CPython
Classifier: Programming Language :: Python :: Implementation :: PyPy
Requires-Python: >=3.10
Requires-Dist: click
Requires-Dist: click<9
Requires-Dist: oauthlib<3.3
Requires-Dist: owslib
Requires-Dist: pystac-client<1
Requires-Dist: pystac[validation]<2
Requires-Dist: python-dateutil<3
Requires-Dist: python-dotenv<1.1.0
Requires-Dist: pyyaml<7
Requires-Dist: requests-oauthlib<1.3.2
Requires-Dist: requests<3
Requires-Dist: setuptools<71
Requires-Dist: spdx-lookup<=0.3.3
Requires-Dist: stac-geoparquet<=0.7.0
Requires-Dist: structlog<22.0
